{
  "active": true,
  "connections": {
    "Schedule Trigger": {
      "main": [
        [
          {
            "node": "HTTP Request",
            "type": "main",
            "index": 0
          }
        ]
      ]
    }
  },
  "createdAt": "2025-07-24T05:13:15.012Z",
  "id": "tgUkJZ7WBRmuGqa4",
  "isArchived": false,
  "meta": null,
  "name": "self-ping",
  "nodes": [
    {
      "parameters": {
        "rule": {
          "interval": [
            {
              "field": "minutes",
              "minutesInterval": 10
            }
          ]
        }
      },
      "type": "n8n-nodes-base.scheduleTrigger",
      "typeVersion": 1.2,
      "position": [
        0,
        0
      ],
      "id": "a60d5f36-80b3-421c-9ff9-3cbb4dcf2572",
      "name": "Schedule Trigger"
    },
    {
      "parameters": {
        "url": "https://n8n-xane.onrender.com/",
        "options": {}
      },
      "type": "n8n-nodes-base.httpRequest",
      "typeVersion": 4.2,
      "position": [
        208,
        0
      ],
      "id": "ff716dda-2544-4bdc-8414-47eff650bb4f",
      "name": "HTTP Request"
    }
  ],
  "origin": "n8n",
  "pinData": {},
  "repo": {
    "owner": "Owais5514",
    "name": "n8n-xane-backup"
  },
  "settings": {
    "executionOrder": "v1"
  },
  "staticData": {
    "node:Schedule Trigger": {
      "recurrenceRules": []
    }
  },
  "tags": [],
  "triggerCount": 1,
  "updatedAt": "2025-07-24T05:13:33.000Z",
  "versionId": "4d397594-0365-4961-b043-6f4ff0dee963"
}